pjisp_template_name/__init__.py
pjisp_template_name-0.2.4.dist-info/entry_points.txt
pjisp_template_name-0.2.4.dist-info/LICENSE
pjisp_template_name-0.2.4.dist-info/WHEEL
pjisp_template_name-0.2.4.dist-info/METADATA
pjisp_template_name-0.2.4.dist-info/RECORD
